tcpatmodem/__init__.py
tcpatmodem/__main__.py
tcpatmodem/atfsm.py
tcpatmodem/frontend.py
tcpatmodem/rawtty.py
tcpatmodem/tcpdialler.py
tcpatmodem/test_atfsm.py
tcpatmodem-0.1.dist-info/LICENSE
tcpatmodem-0.1.dist-info/METADATA
tcpatmodem-0.1.dist-info/WHEEL
tcpatmodem-0.1.dist-info/top_level.txt
tcpatmodem-0.1.dist-info/RECORD
