Metadata-Version: 2.1
Name: tcpatmodem
Version: 0.1
Summary: AT command interpreter and TCP dialler
Home-page: https://github.com/stblassitude/tcpatmodem
Author: Stefan Bethke
Author-email: stb@lassitu.de
License: MIT
Platform: UNKNOWN
